untis_dif_file_writer/__init__.py
untis_dif_file_writer/dif_files_columns.py
untis_dif_file_writer/helpers.py
untis_dif_file_writer/writers.py
untis_dif_file_writer-0.1.3.dist-info/METADATA
untis_dif_file_writer-0.1.3.dist-info/WHEEL
untis_dif_file_writer-0.1.3.dist-info/RECORD
