Metadata-Version: 2.1
Name: untis-dif-file-writer
Version: 0.1.3
Summary: A library to write dif-files from Untis.
Author: Johannes Lieberherr
Author-email: johannes.lieberherr@ttools.ch
Requires-Python: >=3.8
Classifier: Programming Language :: Python :: 3
Classifier: Programming Language :: Python :: 3.8
Classifier: Programming Language :: Python :: 3.9
Classifier: Programming Language :: Python :: 3.10
Classifier: Programming Language :: Python :: 3.11
Classifier: Programming Language :: Python :: 3.12
Requires-Dist: start-end-logging (>=0.1.5,<0.2.0)
Project-URL: GitHub Repository, https://github.com/jlieberherr/untis-dif-file-writer
